{
	"songs": [
	{"id":   0, "age": 1, "year": 2011, "title": "ebiture", "title_kana": "えびちゅああ"},
	{"id":   1, "age": 1, "year": 2011, "title": "なにがなんでも(エビ中ver.)", "title_kana": "なにがなんでも"},
        {"id":   2, "age": 1, "year": 2011, "title": "大爆発NO.1", "title_kana": "だいばくはつなんばあわん"},
        {"id":   3, "age": 1, "year": 2011, "title": "えびぞりダイアモンド!!", "title_kana": "えびぞりだいあもんど"},
        {"id":   4, "age": 1, "year": 2011, "title": "チャイム！", "title_kana": "ちゃいむ"},
        {"id":   5, "age": 1, "year": 2011, "title": "どしゃぶりリグレット", "title_kana": "どしゃぶりりぐれっと"},
        {"id":   6, "age": 1, "year": 2011, "title": "ザ・ティッシュ～とまらない青春～", "title_kana": "ざてぃっしゅとまらないせいしゅん"},
        {"id":   7, "age": 1, "year": 2011, "title": "エビ中一週間", "title_kana": "えびちゅういっしゅうかん"},
        {"id":   8, "age": 1, "year": 2011, "title": "オーマイゴースト?～わたしが悪霊になっても～", "title_kana": "おおまいごおすとわたしがあくりょうになっても"},
        {"id":   9, "age": 1, "year": 2011, "title": "ご存知!エビ中音頭", "title_kana": "ごぞんじえびちゅうおんど"},
        {"id":  10, "age": 1, "year": 2011, "title": "もっと走れっ!!", "title_kana": "もっとはしれ"},
        {"id":  11, "age": 1, "year": 2011, "title": "売れたいエモーション！", "title_kana": "うれたいえもおしょん"},
        {"id":  12, "age": 1, "year": 2011, "title": "永遠に中学生", "title_kana": "えいえんにちゅうがくせい"},
        {"id":  13, "age": 2, "year": 2011, "title": "仮契約のシンデレラ", "title_kana": "かりけいやくのしんでれら"},
        {"id":  14, "age": 2, "year": 2011, "title": "放課後ゲタ箱ロッケンロールMX", "title_kana": "ほうかごげたばころっけんろおるえむえっくす"},
        {"id":  15, "age": 2, "year": 2011, "title": "揚げろ!エビフライ", "title_kana": "あげろえびふらい"},
        {"id":  16, "age": 2, "year": 2011, "title": "歌え!踊れ!エビーダダ!", "title_kana": "うたえおどれえびいだだ"},
        {"id":  17, "age": 2, "year": 2011, "title": "結果オーライ", "title_kana": "けっかおおらい"},
        {"id":  18, "age": 2, "year": 2011, "title": "Go!Go!Here We Go!ロック・リー", "title_kana": "ごおごおひあうぃいごろっくりい"},
        {"id":  19, "age": 2, "year": 2011, "title": "大人はわかってくれない", "title_kana": "おとなはわかってくれない"},
        {"id":  20, "age": 2, "year": 2011, "title": "ほぼブラジル", "title_kana": "ほぼぶらじる"},
        {"id":  21, "age": 2, "year": 2011, "title": "スターダストライト", "title_kana": "すたあだすとらいと"},
        {"id":  22, "age": 2, "year": 2011, "title": "新・青春そのもの", "title_kana": "しんせいしゅんそのもの"},
        {"id":  23, "age": 1, "year": 2011, "title": "エビ中出席番号の歌 その1", "title_kana": "えびちゅうしゅっせきばんごうのうたそのいち"},
        {"id":  24, "age": 1, "year": 2011, "title": "イッショウトモダチ", "title_kana": "いっしょうともだち"},
        {"id":  25, "age": 1, "year": 2011, "title": "約束", "title_kana": "やくそく"},
        {"id":  26, "age": 1, "year": 2011, "title": "また明日", "title_kana": "またあした"},
        {"id":  27, "age": 2, "year": 2011, "title": "梅", "title_kana": "うめ"},
        {"id":  28, "age": 2, "year": 2011, "title": "頑張ってる途中", "title_kana": "がんばってるとちゅう"},
        {"id":  29, "age": 2, "year": 2011, "title": "パクチー", "title_kana": "ぱくちい"},
        {"id":  30, "age": 2, "year": 2011, "title": "大好きだよ", "title_kana": "だいすきだよ"},
        {"id":  31, "age": 2, "year": 2011, "title": "踊るガリ勉中学生", "title_kana": "おどるがりべんちゅうがくせい"},
        {"id":  32, "age": 2, "year": 2011, "title": "手をつなごう", "title_kana": "てをつなごう"},
        {"id":  33, "age": 2, "year": 2011, "title": "禁断のカルマ", "title_kana": "きんだんのかるま"},
        {"id":  34, "age": 2, "year": 2011, "title": "サクラ・ゴーラウンド", "title_kana": "さくらごおらうんど"},
        {"id":  35, "age": 2, "year": 2011, "title": "Lon de Don", "title_kana": "ろんでどん"},
        {"id":  36, "age": 2, "year": 2011, "title": "Another Day", "title_kana": "あなざあでい"},
        {"id":  37, "age": 2, "year": 2011, "title": "Chuning!!(Interlude)", "title_kana": "ちゅうにんぐ"},
        {"id":  38, "age": 2, "year": 2011, "title": "あたしきっと無限ルーパー", "title_kana": "あたしきっとむげんるうぱあ"},
        {"id":  39, "age": 2, "year": 2011, "title": "R-O-B-O-C-K", "title_kana": "ろぼっく"},
        {"id":  40, "age": 2, "year": 2011, "title": "高校廃止法案", "title_kana": "こうこうはいしほうあん"},
        {"id":  41, "age": 2, "year": 2011, "title": "体操", "title_kana": "たいそう"},
        {"id":  42, "age": 2, "year": 2011, "title": "誘惑したいや", "title_kana": "ゆうわくしたいや"},
        {"id":  43, "age": 2, "year": 2011, "title": "チューニング真っ最中", "title_kana": "ちゅうにんぐまっさいちゅう"},
        {"id":  44, "age": 2, "year": 2011, "title": "いい湯かな？", "title_kana": "いいゆかな"},
        {"id":  45, "age": 2, "year": 2011, "title": "中人DANCE MUSIC", "title_kana": "ちゅうにんだんすみゅうじっく"},
        {"id":  46, "age": 2, "year": 2011, "title": "あるあるフラダンス", "title_kana": "あるあるふらだんす"},
        {"id":  47, "age": 2, "year": 2011, "title": "未確認中学生X", "title_kana": "みかくにんちゅうがくせいえっくす"},
        {"id":  48, "age": 2, "year": 2011, "title": "U.B.U.", "title_kana": "うぶ"},
        {"id":  49, "age": 2, "year": 2011, "title": "I'm your MANAGER!!!", "title_kana": "あいむゆあまねえじゃあ"},
        {"id":  50, "age": 2, "year": 2011, "title": "使ってポートフォリオ", "title_kana": "つかってぽおとふぉりお"},
        {"id":  51, "age": 2, "year": 2011, "title": "Thanks! Merry Christmas K", "title_kana": "さんくすめりいくりすますけい"},
        {"id":  52, "age": 2, "year": 2011, "title": "フレ!フレ!サイリウム", "title_kana": "ふれふれさいりうむ"},
        {"id":  53, "age": 2, "year": 2011, "title": "Dear Dear Dear", "title_kana": "でぃあでぃあでぃあ"},
        {"id":  54, "age": 3, "year": 2011, "title": "バタフライエフェクト", "title_kana": "ばたふらいえふぇくと"},
        {"id":  55, "age": 3, "year": 2011, "title": "アンコールの恋", "title_kana": "あんこおるのこい"},
        {"id":  56, "age": 3, "year": 2011, "title": "幸せの貼り紙はいつも背中に", "title_kana": "しあわせのはりがみはいつもせなかに"},
        {"id":  57, "age": 3, "year": 2011, "title": "ラブリースマイリーベイビー", "title_kana": "らぶりいすまいりいべいびい"},
        {"id":  58, "age": 3, "year": 2011, "title": "ハイタテキ!", "title_kana": "はいたてき"},
        {"id":  59, "age": 3, "year": 2011, "title": "涙は似合わない", "title_kana": "なみだはにあわない"},
        {"id":  60, "age": 3, "year": 2011, "title": "I can't stop the loneliness", "title_kana": "あいきゃんとすとっぷざろんりねす"},
        {"id":  61, "age": 3, "year": 2011, "title": "チュパカブラ", "title_kana": "ちゅぱかぶら"},
        {"id":  62, "age": 3, "year": 2011, "title": "二乗の事情", "title_kana": "じじょうのじじょう"},
        {"id":  63, "age": 3, "year": 2011, "title": "金八DANCE MUSIC", "title_kana": "きんぱちだんすみゅうじっく"},
        {"id":  64, "age": 3, "year": 2011, "title": "テブラデスキー～青春リバティ～", "title_kana": "てぶらですきいせいしゅんりばてぃ"},
        {"id":  65, "age": 3, "year": 2011, "title": "キングオブ学芸会のテーマ～Nu Skool Teenage Riot～", "title_kana": "きんぐおぶがくげいかいのてえまにゅうすくうるてぃいねいじらいおっと"},
        {"id":  66, "age": 3, "year": 2011, "title": "私立恵比寿中学の日常(Interlude)：早弁ラップ", "title_kana": "はやべんらっぷ"},
        {"id":  67, "age": 3, "year": 2011, "title": "ちちんぷい", "title_kana": "ちちんぷい"},
        {"id":  68, "age": 3, "year": 2011, "title": "フユコイ", "title_kana": "ふゆこい"},
        {"id":  69, "age": 3, "year": 2011, "title": "PLAYBACK", "title_kana": "ぷれいばっく"},
        {"id":  70, "age": 3, "year": 2011, "title": "大漁恵比寿節", "title_kana": "たいりょうえびすぶし"},
        {"id":  71, "age": 3, "year": 2011, "title": "買い物しようと町田へ", "title_kana": "かいものいこうとまちだへ"},
        {"id":  72, "age": 3, "year": 2011, "title": "私立恵比寿中学の日常(Epilogue)：蛍の光(Demo)", "title_kana": "ほたるのひかり"},
        {"id":  73, "age": 3, "year": 2011, "title": "夏だぜジョニー", "title_kana": "なつだぜじょにい"},
        {"id":  74, "age": 3, "year": 2011, "title": "脳漿炸裂ガール", "title_kana": "のうしょうさくれつがある"},
        {"id":  75, "age": 3, "year": 2011, "title": "吟遊詩人", "title_kana": "ぎんゆうしじん"},
        {"id":  76, "age": 3, "year": 2011, "title": "キャンディロッガー", "title_kana": "きゃんでぃろっがあ"},
        {"id":  77, "age": 3, "year": 2011, "title": "スーパーヒーロー", "title_kana": "すうぱあひいろお"},
        {"id":  78, "age": 3, "year": 2011, "title": "キラキラネスキラネス", "title_kana": "きらきらねすきらねす"},
        {"id":  79, "age": 3, "year": 2011, "title": "こりゃめでてぇな", "title_kana": "こりゃめでてぇな"},
        {"id":  80, "age": 3, "year": 2011, "title": "きっとインフィニティー！", "title_kana": "きんといんふぃにてぃい"},
        {"id":  81, "age": 3, "year": 2011, "title": "埋めてあげたい", "title_kana": "うめてあげたい"},
        {"id":  82, "age": 3, "year": 2011, "title": "ゼッテーアナーキー", "title_kana": "ぜってえあなあきい"},
        {"id":  83, "age": 3, "year": 2011, "title": "春休みモラトリアム中学生", "title_kana": "はるやすみもらとりあむちゅうがくせい"},
        {"id":  84, "age": 3, "year": 2011, "title": "ポップコーントーン", "title_kana": "ぽっぷこおんとおん"},
        {"id":  85, "age": 3, "year": 2011, "title": "面皰", "title_kana": "にきび"},
        {"id":  86, "age": 3, "year": 2011, "title": "エビ中出席番号の歌 その2", "title_kana": "えびちゅうしゅっせきばんごうのうたそのに"},
        {"id":  87, "age": 3, "year": 2011, "title": "マブいラガタイフーン(Interlude)", "title_kana": "まぶいらがたいふうん"},
        {"id":  88, "age": 3, "year": 2011, "title": "MISSION SURVIVOR", "title_kana": "みっしょんさばいばあ"},
        {"id":  89, "age": 3, "year": 2011, "title": "ナチュメロらんでぶー", "title_kana": "なちゅめろらんでぶう"},
        {"id":  90, "age": 3, "year": 2011, "title": "あな秋いんざ夕景", "title_kana": "あなあきいんざゆうけい"},
        {"id":  91, "age": 3, "year": 2011, "title": "お願いジーザス", "title_kana": "おねがいじいざす"},
        {"id":  92, "age": 3, "year": 2011, "title": "全力☆ランナー", "title_kana": "ぜんりょくらんなあ"},
        {"id":  93, "age": 3, "year": 2011, "title": "参枚目のタフガキ", "title_kana": "さんまいめのたふがき"},
        {"id":  94, "age": 3, "year": 2011, "title": "まっすぐ", "title_kana": "まっすぐ"},
        {"id":  95, "age": 3, "year": 2011, "title": "summer dejavu", "title_kana": "さまーでじゃびゅ"},
        {"id":  96, "age": 3, "year": 2011, "title": "イイトモ", "title_kana": "いいとも"},
        {"id":  97, "age": 3, "year": 2011, "title": "CHAN-CHARA-CHAN", "title_kana": "ちゃんちゃらちゃん"},
        {"id":  98, "age": 3, "year": 2011, "title": "サドンデス", "title_kana": "さどんです"},
        {"id":  99, "age": 4, "year": 2011, "title": "ゑびすとてたまわんせむ", "title_kana": "えびすとてたまわんせむ"},
        {"id": 100, "age": 4, "year": 2011, "title": "制服“報連相”ファンク", "title_kana": "せいふくほうれんそうふぁんく"},
        {"id": 101, "age": 4, "year": 2011, "title": "感情電車", "title_kana": "かんじょうでんしゃ"},
        {"id": 102, "age": 4, "year": 2011, "title": "紅の詩", "title_kana": "くれないのうた"},
        {"id": 103, "age": 4, "year": 2011, "title": "コミックガール", "title_kana": "こみっくがある"},
        {"id": 104, "age": 4, "year": 2011, "title": "さよならばいばいまたあした", "title_kana": "さよならばいばいまたあした"},
        {"id": 105, "age": 4, "year": 2011, "title": "なないろ", "title_kana": "なないろ"},
        {"id": 106, "age": 4, "year": 2011, "title": "君のままで", "title_kana": "きみのままで"},
        {"id": 107, "age": 4, "year": 2011, "title": "藍色のMonday", "title_kana": "あいいろのまんでい"},
        {"id": 108, "age": 4, "year": 2011, "title": "春の嵐", "title_kana": "はるのあらし"},
        {"id": 109, "age": 4, "year": 2011, "title": "フォーエバー中坊", "title_kana": "ふぉおえばあちゅうぼう"},
        {"id": 110, "age": 4, "year": 2011, "title": "YELL", "title_kana": "ええる"},
        {"id": 111, "age": 4, "year": 2011, "title": "シンガロン・シンガソン", "title_kana": "しんがろんしんがそん"},
        {"id": 112, "age": 4, "year": 2011, "title": "EBINOMICS", "title_kana": "えびのみくす"},
        {"id": 113, "age": 4, "year": 2011, "title": "靴紐とファンファーレ", "title_kana": "くつひもとふぁんふぁあれ"},
        {"id": 114, "age": 4, "year": 2011, "title": "HOT UP!!!", "title_kana": "ほっとあっぷ"},
        {"id": 115, "age": 5, "year": 2011, "title": "響", "title_kana": "ひびき"},
        {"id": 116, "age": 5, "year": 2011, "title": "日記", "title_kana": "にっき"},
        {"id": 117, "age": 5, "year": 2011, "title": "でかどんでん", "title_kana": "でかどんでん"},
        {"id": 118, "age": 5, "year": 2011, "title": "熟女になっても", "title_kana": "じゅくじょになっても"},
        {"id": 119, "age": 5, "year": 2011, "title": "スウィーテスト・多忙。", "title_kana": "すうぃいてすとたぼう"},
        {"id": 120, "age": 5, "year": 2011, "title": "イート・ザ・大目玉", "title_kana": "いいとざおおめだま"},
        {"id": 121, "age": 5, "year": 2011, "title": "朝顔", "title_kana": "あさがお"},
        {"id": 122, "age": 5, "year": 2011, "title": "BUZZER BEATER", "title_kana": "ぶざあびいたあ"},
        {"id": 123, "age": 5, "year": 2011, "title": "曇天", "title_kana": "どんてん"},
        {"id": 124, "age": 5, "year": 2011, "title": "明日もきっと70点", "title_kana": "あしたもきっとななじってん"},
        {"id": 125, "age": 5, "year": 2011, "title": "Family Complex", "title_kana": "ふぁみりいこんぷれっくす"},
        {"id": 126, "age": 5, "year": 2011, "title": "踊るロクデナシ", "title_kana": "おどるろくでなし"},
        {"id": 127, "age": 4, "year": 2011, "title": "日進月歩", "title_kana": "にっしんげっぽ"},
        {"id": 128, "age": 5, "year": 2011, "title": "星の数え方", "title_kana": "ほしのかぞえかた"},
        {"id": 129, "age": 5, "year": 2011, "title": "COLOR", "title_kana": "からあ"},
        {"id": 130, "age": 5, "year": 2011, "title": "元気しかない！", "title_kana": "げんきしかない"},
        {"id": 131, "age": 5, "year": 2011, "title": "トレンディガール", "title_kana": "とれんでぃがある"},
        {"id": 132, "age": 5, "year": 2011, "title": "結ばれた想い", "title_kana": "むすばれたおもい"},
        {"id": 133, "age": 5, "year": 2011, "title": "青い青い星の名前", "title_kana": "あおいあおいほしのなまえ"},
        {"id": 134, "age": 5, "year": 2011, "title": "あなたのダンスで騒がしい", "title_kana": "あなたのだんすでさわがしい"},
        {"id": 135, "age": 5, "year": 2011, "title": "ちがうの", "title_kana": "ちがうの"},
        {"id": 136, "age": 5, "year": 2011, "title": "SHAKE! SHAKE!", "title_kana": "しぇいくしぇいく"},
        {"id": 137, "age": 5, "year": 2011, "title": "愛のレンタル", "title_kana": "あいのれんたる"},
        {"id": 138, "age": 5, "year": 2011, "title": "ジャンプ", "title_kana": "じゃんぷ"},
        {"id": 139, "age": 5, "year": 2011, "title": "I'll be here", "title_kana": "あいるびいひあ"},
        {"id": 140, "age": 5, "year": 2011, "title": "PANDORA", "title_kana": "ぱんどら"},
        {"id": 141, "age": 5, "year": 2011, "title": "シングルTONEでお願い", "title_kana": "しんぐるとおんでおねがい"},
        {"id": 142, "age": 5, "year": 2011, "title": "オメカシ・フィーバー", "title_kana": "おめかしふぃいばあ"},
        {"id": 143, "age": 5, "year": 2011, "title": "HISTORY", "title_kana": "ひすとりい"},
        {"id": 144, "age": 5, "year": 2011, "title": "Sweet of Sweet～君に届くまで～", "title_kana": "すいいとおぶすいいときみにとどくまで"},
        {"id": 145, "age": 5, "year": 2011, "title": "23回目のサマーナイト", "title_kana": "にじゅうさんかいめのさまあないと"},
        {"id": 146, "age": 5, "year": 2011, "title": "イエローライト", "title_kana": "いえろおらいと"},
        {"id": 147, "age": 6, "year": 2011, "title": "イヤフォン・ライオット", "title_kana": "いやふぉんらいおっと"},
        {"id": 148, "age": 6, "year": 2011, "title": "Anytime, Anywhere", "title_kana": "えにいたいむえにいうぇあ"},
        {"id": 149, "age": 6, "year": 2011, "title": "ハッピーエンドとそれから", "title_kana": "はっぴいえんどとそれから"},
        {"id": 150, "age": 6, "year": 2011, "title": "きゅるん", "title_kana": "きゅるん"},
        {"id": 151, "age": 6, "year": 2011, "title": "トキメキ的週末論", "title_kana": "ときめきてきしゅうまつろん"},
        {"id": 152, "age": 6, "year": 2011, "title": "シュガーグレーズ", "title_kana": "しゅがあぐれえず"},
        {"id": 153, "age": 6, "year": 2011, "title": "さよなら秘密基地", "title_kana": "さよならひみつきち"},
        {"id": 154, "age": 6, "year": 2011, "title": "ナガレボシ", "title_kana": "ながれぼし"},
        {"id": 155, "age": 6, "year": 2011, "title": "宇宙は砂時計", "title_kana": "うちゅうはすなどけい"},
        {"id": 156, "age": 6, "year": 2011, "title": "青春ゾンビィィズ", "title_kana": "せいしゅんぞんびぃぃず"},
        {"id": 157, "age": 6, "year": 2011, "title": "新未来センセーション", "title_kana": "しんみらいせんせいしょん"},
        {"id": 158, "age": 6, "year": 2011, "title": "Bang Bang Beat", "title_kana": "ばんばんびいと"},
        {"id": 159, "age": 6, "year": 2011, "title": "ヘロー", "title_kana": "へろお"},
        {"id": 160, "age": 6, "year": 2011, "title": "エビ中出席番号の歌 その3", "title_kana": "えびちゅうしゅっせきばんごうのうたそのさん"},
        {"id": 161, "age": 6, "year": 2011, "title": "まだ×2売れたいエモーション!", "title_kana": "まだまだうれたいえもおしょん"},
        {"id": 162, "age": 6, "year": 2011, "title": "ボイジャー", "title_kana": "ぼいじゃあ"},
        {"id": 163, "age": 7, "year": 2011, "title": "kyo-do?", "title_kana": "きょおどお"},
        {"id": 164, "age": 7, "year": 2011, "title": "ジブンアップデート", "title_kana": "じぶんあっぷでえと"},
        {"id": 165, "age": 7, "year": 2011, "title": "はみだせGirls", "title_kana": "はみだせがあるず"},
        {"id": 166, "age": 7, "year": 2011, "title": "Summer Glitter", "title_kana": "さまあぐりったあ"},
        {"id": 167, "age": 7, "year": 2011, "title": "BLUE DIZZINESS", "title_kana": "ぶるうでぃじねす"},
        {"id": 168, "age": 7, "year": 2011, "title": "CRYSTAL DROP", "title_kana": "くりすたるどろっぷ"},
        {"id": 169, "age": 7, "year": 2011, "title": "トーキョーズ・ウェイ！", "title_kana": "とおきょおずうぇい"},
        {"id": 170, "age": 7, "year": 2011, "title": "TWINKLE WINK", "title_kana": "とぅうぃんくるうぃんく"},
        {"id": 171, "age": 7, "year": 2011, "title": "Knock You Out!", "title_kana": "のっくゆうあうと"},
        {"id": 172, "age": 7, "year": 2011, "title": "DRAMA QUEEN", "title_kana": "どらまくいいん"}
    ]
}
